AndroidTelePorter/__init__.py
AndroidTelePorter/androidsession.py
AndroidTelePorter/constants/__init__.py
AndroidTelePorter/constants/datacenters.py
AndroidTelePorter/managers/__init__.py
AndroidTelePorter/managers/tgnetmanager.py
AndroidTelePorter/managers/userconfigmanager.py
AndroidTelePorter/models/__init__.py
AndroidTelePorter/models/auth.py
AndroidTelePorter/models/datacenter.py
AndroidTelePorter/models/headers.py
AndroidTelePorter/models/ip.py
AndroidTelePorter/models/salt.py
AndroidTelePorter/models/tgnet_session.py
AndroidTelePorter/utils/__init__.py
AndroidTelePorter/utils/auth_key.py
AndroidTelePorter/utils/filesmanager.py
AndroidTelePorter/utils/nativebytebuffer.py
AndroidTelePorter-1.1.1.dist-info/LICENSE
AndroidTelePorter-1.1.1.dist-info/METADATA
AndroidTelePorter-1.1.1.dist-info/WHEEL
AndroidTelePorter-1.1.1.dist-info/top_level.txt
AndroidTelePorter-1.1.1.dist-info/RECORD
