Metadata-Version: 2.1
Name: AndroidTelePorter
Version: 1.1.1
Summary: Serializer and deserializer for mobile telegram session
Home-page: https://github.com/batreller/AndroidTelePorter
Author: batreller
Author-email: <batreller@gmail.com>
License: MIT
Classifier: Development Status :: 5 - Production/Stable
Classifier: Intended Audience :: Developers
Classifier: Programming Language :: Python :: 3
Classifier: Operating System :: OS Independent
Requires-Python: >=3.9
License-File: LICENSE
Requires-Dist: telethon
Requires-Dist: lxml~=5.2.2
Requires-Dist: opentele~=1.15.1
Requires-Dist: setuptools~=72.1.0
Requires-Dist: Pyrogram~=2.0.106
